xbudget/__init__.py
xbudget/collect.py
xbudget/presets.py
xbudget/version.py
xbudget/conventions/MOM6.yaml
xbudget/conventions/MOM6_3Donly.yaml
xbudget/conventions/MOM6_drift.yaml
xbudget/conventions/MOM6_surface.yaml
xbudget-0.5.0.dist-info/METADATA
xbudget-0.5.0.dist-info/WHEEL
xbudget-0.5.0.dist-info/licenses/LICENSE
xbudget-0.5.0.dist-info/RECORD
