Metadata-Version: 2.4
Name: xbudget
Version: 0.5.0
Summary: Helper functions and meta-data conventions for wrangling finite-volume ocean model budgets
Project-URL: Homepage, https://github.com/hdrake/xbudget
Project-URL: Bugs/Issues/Features, https://github.com/hdrake/xbudget/issues
Author-email: "Henri F. Drake" <hfdrake@uci.edu>
License-File: LICENSE
Classifier: License :: OSI Approved :: GNU General Public License v3 (GPLv3)
Classifier: Operating System :: OS Independent
Classifier: Programming Language :: Python :: 3
Requires-Python: >=3.8
Requires-Dist: numpy
Requires-Dist: xarray
Requires-Dist: xgcm>=0.9.0
